auto_swagger/__init__.py
auto_swagger/main.py
auto_swagger/config/__init__.py
auto_swagger/config/settings.py
auto_swagger/finetune/__init__.py
auto_swagger/finetune/finetune.py
auto_swagger/finetune/prepare_finetune_data.py
auto_swagger/parser/__init__.py
auto_swagger/parser/parser.py
auto_swagger/swagger_generator/__init__.py
auto_swagger/swagger_generator/file_handler.py
auto_swagger/swagger_generator/generator_config.py
auto_swagger/swagger_generator/git_handler.py
auto_swagger/swagger_generator/llm_handler.py
auto_swagger/swagger_generator/models.py
auto_swagger-0.1.1.dist-info/METADATA
auto_swagger-0.1.1.dist-info/WHEEL
auto_swagger-0.1.1.dist-info/entry_points.txt
auto_swagger-0.1.1.dist-info/licenses/LICENSE
auto_swagger-0.1.1.dist-info/RECORD
