Metadata-Version: 2.4
Name: auto-swagger
Version: 0.1.1
Summary: Automatically generate Swagger/OpenAPI documentation for Express.js APIs using NLP and LLMs
Project-URL: Homepage, https://github.com/restartdk/auto_swagger
Project-URL: Repository, https://github.com/restartdk/auto_swagger
Project-URL: Issues, https://github.com/restartdk/auto_swagger/issues
Author: restartdk, paulopasso, albipuliga
License: MIT
License-File: LICENSE
Keywords: api-documentation,automation,documentation-generator,express,expressjs,llm,nlp,openapi,swagger
Classifier: Intended Audience :: Developers
Classifier: License :: OSI Approved :: MIT License
Classifier: Programming Language :: Python :: 3.12
Classifier: Topic :: Internet :: WWW/HTTP :: HTTP Servers
Classifier: Topic :: Software Development :: Documentation
Requires-Python: >=3.12
Requires-Dist: accelerate==1.6.0
Requires-Dist: annotated-types==0.7.0
Requires-Dist: bitsandbytes==0.42.0
Requires-Dist: blis==1.3.0
Requires-Dist: catalogue==2.0.10
Requires-Dist: certifi==2025.1.31
Requires-Dist: cffi==1.17.1
Requires-Dist: charset-normalizer==3.4.1
Requires-Dist: click==8.1.8
Requires-Dist: cloudpathlib==0.21.0
Requires-Dist: confection==0.1.5
Requires-Dist: cryptography==44.0.2
Requires-Dist: cymem==2.0.11
Requires-Dist: datasets>=2.14.4
Requires-Dist: deprecated==1.2.18
Requires-Dist: filelock==3.18.0
Requires-Dist: fsspec==2025.3.2
Requires-Dist: gitdb==4.0.12
Requires-Dist: gitpython==3.1.44
Requires-Dist: huggingface-hub>=0.34.0
Requires-Dist: idna==3.10
Requires-Dist: jinja2==3.1.6
Requires-Dist: langcodes==3.5.0
Requires-Dist: language-data==1.3.0
Requires-Dist: marisa-trie==1.2.1
Requires-Dist: markdown-it-py==3.0.0
Requires-Dist: markupsafe==3.0.2
Requires-Dist: mdurl==0.1.2
Requires-Dist: mpmath==1.3.0
Requires-Dist: murmurhash==1.0.12
Requires-Dist: networkx==3.4.2
Requires-Dist: numpy==2.2.4
Requires-Dist: packaging==25.0
Requires-Dist: peft>=0.15.2
Requires-Dist: pillow==11.2.1
Requires-Dist: preshed==3.0.9
Requires-Dist: psutil==7.0.0
Requires-Dist: pycparser==2.22
Requires-Dist: pydantic-core==2.33.1
Requires-Dist: pygithub==2.6.1
Requires-Dist: pygments==2.19.1
Requires-Dist: pyjwt==2.10.1
Requires-Dist: pynacl==1.5.0
Requires-Dist: pyyaml==6.0.2
Requires-Dist: regex==2024.11.6
Requires-Dist: requests==2.32.3
Requires-Dist: rich==14.0.0
Requires-Dist: safetensors==0.5.3
Requires-Dist: scipy==1.15.2
Requires-Dist: setuptools==78.1.0
Requires-Dist: shellingham==1.5.4
Requires-Dist: smart-open==7.1.0
Requires-Dist: smmap==5.0.2
Requires-Dist: spacy-legacy==3.0.12
Requires-Dist: spacy-loggers==1.0.5
Requires-Dist: spacy>=3.8.6
Requires-Dist: srsly==2.5.1
Requires-Dist: sympy==1.13.1
Requires-Dist: thinc==8.3.6
Requires-Dist: tokenizers==0.21.1
Requires-Dist: torch==2.6.0
Requires-Dist: torchvision==0.21.0
Requires-Dist: tqdm==4.67.1
Requires-Dist: transformers>=4.55.0
Requires-Dist: typer==0.15.2
Requires-Dist: typing-extensions==4.13.2
Requires-Dist: typing-inspection==0.4.0
Requires-Dist: urllib3==2.4.0
Requires-Dist: wasabi==1.1.3
Requires-Dist: weasel==0.4.1
Requires-Dist: wheel>=0.45.1
Requires-Dist: wrapt==1.17.2
